parafilt/__init__.py
parafilt/base.py
parafilt/filters.py
parafilt/version.py
parafilt-0.1.2b0.dist-info/LICENSE
parafilt-0.1.2b0.dist-info/METADATA
parafilt-0.1.2b0.dist-info/WHEEL
parafilt-0.1.2b0.dist-info/top_level.txt
parafilt-0.1.2b0.dist-info/RECORD
