Metadata-Version: 2.1
Name: parafilt
Version: 0.1.2b0
Summary: ParaFilt is a Python package that provides a collection of parallel adaptive filter implementations for efficient signal processing applications.
Home-page: https://github.com/nuniz/ParaFilt
Author: Asaf Zorea
Author-email: zoreasaf@gmail.com
License: MIT
Classifier: Programming Language :: Python :: 3
Classifier: License :: OSI Approved :: MIT License
Classifier: Operating System :: OS Independent
Requires-Python: >=3.6
License-File: LICENSE
Requires-Dist: torch
